[{
    "blockIndex": 0,
    "gridIndex": [
        32,
        33,
        40,
        41
    ]
},
{
    "blockIndex": 1,
    "gridIndex": [
        48,
        47,
        46,
        39
    ]
},
{
    "blockIndex": 2,
    "gridIndex": [
        45,
        38,
        37,
        30
    ]
},
{
    "blockIndex": 3,
    "gridIndex": [
        44,
        43,
        42,
        36
    ]
},
{
    "blockIndex": 4,
    "gridIndex": [
        35,
        28,
        29,
        22
    ]
},
{
    "blockIndex": 5,
    "gridIndex": [
        21,
        14,
        15,
        16,
        23
    ]
},
{
    "blockIndex": 6,
    "gridIndex": [
        7,
        0,
        1
    ]
},
{
    "blockIndex": 7,
    "gridIndex": [
        8,
        9,
        10,
        17
    ]
},
{
    "blockIndex": 8,
    "gridIndex": [
        31,
        24,
        25
    ]
},
{
    "blockIndex": 9,
    "gridIndex": [
        26,
        27,
        34,
        20
    ]
},
{
    "blockIndex": 10,
    "gridIndex": [
        13,
        6,
        12
    ]
},
{
    "blockIndex": 11,
    "gridIndex": [
        19,
        18,
        11,
        4,
        5
    ]
},
{
    "blockIndex": 12,
    "gridIndex": [
        3,
        2
    ]
}]